blastdock/__init__.py
blastdock/__main__.py
blastdock/_version.py
blastdock/cli.py
blastdock/constants.py
blastdock/exceptions.py
blastdock/main_cli.py
blastdock/cli/__init__.py
blastdock/cli/config_commands.py
blastdock/cli/deploy.py
blastdock/cli/diagnostics.py
blastdock/cli/main.py
blastdock/cli/marketplace.py
blastdock/cli/monitoring.py
blastdock/cli/performance.py
blastdock/cli/security.py
blastdock/cli/templates.py
blastdock/config/__init__.py
blastdock/config/environment.py
blastdock/config/manager.py
blastdock/config/models.py
blastdock/config/persistence.py
blastdock/config/profiles.py
blastdock/config/schema.py
blastdock/config/simple_models.py
blastdock/config/watchers.py
blastdock/core/__init__.py
blastdock/core/config.py
blastdock/core/deployment_manager.py
blastdock/core/domain.py
blastdock/core/monitor.py
blastdock/core/template_manager.py
blastdock/core/traefik.py
blastdock/docker/__init__.py
blastdock/docker/client.py
blastdock/docker/compose.py
blastdock/docker/containers.py
blastdock/docker/errors.py
blastdock/docker/health.py
blastdock/docker/images.py
blastdock/docker/networks.py
blastdock/docker/volumes.py
blastdock/domains/__init__.py
blastdock/domains/manager.py
blastdock/domains/validator.py
blastdock/marketplace/__init__.py
blastdock/marketplace/installer.py
blastdock/marketplace/marketplace.py
blastdock/marketplace/repository.py
blastdock/migration/__init__.py
blastdock/migration/traefik_migrator.py
blastdock/models/__init__.py
blastdock/models/domain.py
blastdock/models/port.py
blastdock/models/project.py
blastdock/models/template.py
blastdock/models/traefik.py
blastdock/monitoring/__init__.py
blastdock/monitoring/alert_manager.py
blastdock/monitoring/dashboard.py
blastdock/monitoring/health_checker.py
blastdock/monitoring/log_analyzer.py
blastdock/monitoring/metrics_collector.py
blastdock/monitoring/web_dashboard.py
blastdock/performance/__init__.py
blastdock/performance/async_loader.py
blastdock/performance/benchmarks.py
blastdock-2.0.0.dist-info/licenses/LICENSE
blastdock-2.0.0.dist-info/METADATA
blastdock-2.0.0.dist-info/WHEEL
blastdock-2.0.0.dist-info/entry_points.txt
blastdock-2.0.0.dist-info/top_level.txt
blastdock-2.0.0.dist-info/RECORD
